odoo/addons/purchase_request_operating_unit/README.rst
odoo/addons/purchase_request_operating_unit/__init__.py
odoo/addons/purchase_request_operating_unit/__manifest__.py
odoo/addons/purchase_request_operating_unit/i18n/fr.po
odoo/addons/purchase_request_operating_unit/i18n/it.po
odoo/addons/purchase_request_operating_unit/i18n/pt.po
odoo/addons/purchase_request_operating_unit/i18n/purchase_request_operating_unit.pot
odoo/addons/purchase_request_operating_unit/model/__init__.py
odoo/addons/purchase_request_operating_unit/model/purchase_request.py
odoo/addons/purchase_request_operating_unit/readme/CONTRIBUTORS.rst
odoo/addons/purchase_request_operating_unit/readme/DESCRIPTION.rst
odoo/addons/purchase_request_operating_unit/readme/USAGE.rst
odoo/addons/purchase_request_operating_unit/security/purchase_security.xml
odoo/addons/purchase_request_operating_unit/static/description/icon.png
odoo/addons/purchase_request_operating_unit/static/description/index.html
odoo/addons/purchase_request_operating_unit/tests/__init__.py
odoo/addons/purchase_request_operating_unit/tests/test_purchase_request_operating_unit.py
odoo/addons/purchase_request_operating_unit/tests/test_purchase_request_to_rfq_operating_unit.py
odoo/addons/purchase_request_operating_unit/view/purchase_request_view.xml
odoo/addons/purchase_request_operating_unit/wizard/__init__.py
odoo/addons/purchase_request_operating_unit/wizard/purchase_request_line_make_purchase_order.py
odoo/addons/purchase_request_operating_unit/wizard/purchase_request_line_make_purchase_order_view.xml
odoo14_addon_purchase_request_operating_unit-14.0.1.0.1.dev8.dist-info/METADATA
odoo14_addon_purchase_request_operating_unit-14.0.1.0.1.dev8.dist-info/WHEEL
odoo14_addon_purchase_request_operating_unit-14.0.1.0.1.dev8.dist-info/top_level.txt
odoo14_addon_purchase_request_operating_unit-14.0.1.0.1.dev8.dist-info/RECORD
