Metadata-Version: 2.1
Name: odoo14-addon-purchase_request_operating_unit
Version: 14.0.1.0.1.dev8
Summary: Operating Unit in Purchase Requests
Home-page: https://github.com/OCA/operating-unit
Author: Eficent, SerpentCS, Odoo Community Association (OCA)
Author-email: support@odoo-community.org
License: LGPL-3
Classifier: Programming Language :: Python
Classifier: Framework :: Odoo
Classifier: Framework :: Odoo :: 14.0
Classifier: License :: OSI Approved :: GNU Lesser General Public License v3 (LGPLv3)
Requires-Python: >=3.6
Requires-Dist: odoo14-addon-purchase-operating-unit
Requires-Dist: odoo14-addon-purchase-request
Requires-Dist: odoo<14.1dev,>=14.0a
